<?xml version="1.0" encoding="UTF-8"?>
<objects serializationModel="Studio.02.01.00">
	<object class="Event" id="{820a4664-1547-489e-8e0d-79f4dbad85a5}">
		<property name="name">
			<value>engine_stop_interior</value>
		</property>
		<property name="outputFormat">
			<value>1</value>
		</property>
		<relationship name="folder">
			<destination>{262dcba8-cf41-4cd4-9cc0-9e8f3ccb5c75}</destination>
		</relationship>
		<relationship name="mixer">
			<destination>{18f35840-424f-4a0b-a61a-4b9469141d13}</destination>
		</relationship>
		<relationship name="masterTrack">
			<destination>{9f260dff-d5b9-42f7-b9b4-b78e721c113a}</destination>
		</relationship>
		<relationship name="mixerInput">
			<destination>{b474e3e9-0115-453f-bdcc-2926ffe39b29}</destination>
		</relationship>
		<relationship name="automatableProperties">
			<destination>{4bb1fc46-b2b7-4da5-b62e-a9780a7f27c4}</destination>
		</relationship>
		<relationship name="markerTracks">
			<destination>{9e3c4ecc-2a7e-41cb-9229-17d5fcf775ae}</destination>
		</relationship>
		<relationship name="groupTracks">
			<destination>{cb504cd7-bbad-4091-a3d1-d8c4bfccd9e6}</destination>
			<destination>{1e36a3bb-c39c-43dc-8f5b-afb8cc704f9d}</destination>
		</relationship>
		<relationship name="timeline">
			<destination>{aec044e7-ad81-4f56-a4c7-284c649cfcbc}</destination>
		</relationship>
		<relationship name="parameters">
			<destination>{27cfd451-160f-4898-bf67-5e7b38c25928}</destination>
		</relationship>
		<relationship name="banks">
			<destination>{31cfecdb-f95d-4775-9330-8bb4c8f0d520}</destination>
		</relationship>
	</object>
	<object class="EventMixer" id="{18f35840-424f-4a0b-a61a-4b9469141d13}">
		<relationship name="masterBus">
			<destination>{1cdf786d-bf74-4ab1-a01d-48adb4f69f99}</destination>
		</relationship>
	</object>
	<object class="MasterTrack" id="{9f260dff-d5b9-42f7-b9b4-b78e721c113a}">
		<relationship name="mixerGroup">
			<destination>{1cdf786d-bf74-4ab1-a01d-48adb4f69f99}</destination>
		</relationship>
	</object>
	<object class="MixerInput" id="{b474e3e9-0115-453f-bdcc-2926ffe39b29}">
		<relationship name="effectChain">
			<destination>{4e8373c8-24aa-4834-bc55-1190664c8754}</destination>
		</relationship>
		<relationship name="panner">
			<destination>{39401020-32c5-4d6e-8c50-fd2de21a8f3a}</destination>
		</relationship>
		<relationship name="output">
			<destination>{b10f6de2-c9e1-4c6c-bd81-8ce39937cd49}</destination>
		</relationship>
	</object>
	<object class="EventAutomatableProperties" id="{4bb1fc46-b2b7-4da5-b62e-a9780a7f27c4}">
		<property name="maxVoices">
			<value>1</value>
		</property>
		<property name="priority">
			<value>4</value>
		</property>
	</object>
	<object class="MarkerTrack" id="{9e3c4ecc-2a7e-41cb-9229-17d5fcf775ae}" />
	<object class="GroupTrack" id="{cb504cd7-bbad-4091-a3d1-d8c4bfccd9e6}">
		<relationship name="automationTracks">
			<destination>{13592e3c-b3c1-425f-abf2-c004677f893a}</destination>
		</relationship>
		<relationship name="modules">
			<destination>{3936a100-d799-4274-8130-c980084c16fe}</destination>
		</relationship>
		<relationship name="mixerGroup">
			<destination>{d22bdf60-9f1b-4887-9d08-aacd62f8c707}</destination>
		</relationship>
	</object>
	<object class="GroupTrack" id="{1e36a3bb-c39c-43dc-8f5b-afb8cc704f9d}">
		<relationship name="modules">
			<destination>{3c427e88-482f-4c76-9a79-0e17dc8beb9d}</destination>
		</relationship>
		<relationship name="mixerGroup">
			<destination>{35eb8902-7493-41f8-bec1-469c17629c2a}</destination>
		</relationship>
	</object>
	<object class="Timeline" id="{aec044e7-ad81-4f56-a4c7-284c649cfcbc}">
		<relationship name="modules">
			<destination>{3936a100-d799-4274-8130-c980084c16fe}</destination>
			<destination>{3c427e88-482f-4c76-9a79-0e17dc8beb9d}</destination>
		</relationship>
	</object>
	<object class="ParameterProxy" id="{27cfd451-160f-4898-bf67-5e7b38c25928}">
		<relationship name="preset">
			<destination>{e3e98b0f-2ad6-4388-b2b8-ad7c30ab75bb}</destination>
		</relationship>
	</object>
	<object class="EventMixerMaster" id="{1cdf786d-bf74-4ab1-a01d-48adb4f69f99}">
		<property name="volume">
			<value>10</value>
		</property>
		<relationship name="effectChain">
			<destination>{c8fccff2-e353-4bfa-9a5f-6239eb4a8797}</destination>
		</relationship>
		<relationship name="panner">
			<destination>{59499838-5217-469e-93ae-0335e5dce553}</destination>
		</relationship>
		<relationship name="mixer">
			<destination>{18f35840-424f-4a0b-a61a-4b9469141d13}</destination>
		</relationship>
	</object>
	<object class="MixerBusEffectChain" id="{4e8373c8-24aa-4834-bc55-1190664c8754}">
		<relationship name="effects">
			<destination>{dd3abd6c-e8f1-4128-8494-b23ba3a1752d}</destination>
		</relationship>
	</object>
	<object class="MixerBusPanner" id="{39401020-32c5-4d6e-8c50-fd2de21a8f3a}" />
	<object class="AutomationTrack" id="{13592e3c-b3c1-425f-abf2-c004677f893a}">
		<relationship name="automator">
			<destination>{073b6dc3-8401-4ed9-bdb1-5968bfe86d37}</destination>
		</relationship>
	</object>
	<object class="SingleSound" id="{3936a100-d799-4274-8130-c980084c16fe}">
		<property name="triggerProbabilityEnabled">
			<value>true</value>
		</property>
		<property name="length">
			<value>24</value>
		</property>
		<property name="voiceStealing">
			<value>3</value>
		</property>
		<property name="name">
			<value>/engines_tanks/tank00/tank00_engine_int_stop</value>
		</property>
		<property name="volume">
			<value>6</value>
		</property>
		<relationship name="fadeOutCurve">
			<destination>{05eb4853-80df-4b6c-877e-851724d4035e}</destination>
		</relationship>
		<relationship name="audioFile">
			<destination>{0fb0f9ff-a4c2-461d-9d46-f287e06a803a}</destination>
		</relationship>
	</object>
	<object class="EventMixerGroup" id="{d22bdf60-9f1b-4887-9d08-aacd62f8c707}">
		<property name="name">
			<value>layer00</value>
		</property>
		<relationship name="automators">
			<destination>{073b6dc3-8401-4ed9-bdb1-5968bfe86d37}</destination>
		</relationship>
		<relationship name="effectChain">
			<destination>{38ef1cd4-1a05-4c6a-9699-2012ae094c9f}</destination>
		</relationship>
		<relationship name="panner">
			<destination>{455c420a-4e02-4d39-a3fd-e0e42920ee1b}</destination>
		</relationship>
		<relationship name="output">
			<destination>{1cdf786d-bf74-4ab1-a01d-48adb4f69f99}</destination>
		</relationship>
	</object>
	<object class="EventSound" id="{3c427e88-482f-4c76-9a79-0e17dc8beb9d}">
		<property name="start">
			<value>8</value>
		</property>
		<property name="length">
			<value>27</value>
		</property>
		<relationship name="event">
			<destination>{cc1dc982-1d61-4606-8ae1-e8ced7f25454}</destination>
		</relationship>
	</object>
	<object class="EventMixerGroup" id="{35eb8902-7493-41f8-bec1-469c17629c2a}">
		<property name="volume">
			<value>-12</value>
		</property>
		<property name="name">
			<value>cooldown_interior</value>
		</property>
		<relationship name="effectChain">
			<destination>{19208194-d291-49cf-b7a4-17d2797cdeb0}</destination>
		</relationship>
		<relationship name="panner">
			<destination>{d64d4f67-1305-4f48-93e7-524becf09849}</destination>
		</relationship>
		<relationship name="output">
			<destination>{1cdf786d-bf74-4ab1-a01d-48adb4f69f99}</destination>
		</relationship>
	</object>
	<object class="MixerBusEffectChain" id="{c8fccff2-e353-4bfa-9a5f-6239eb4a8797}">
		<relationship name="effects">
			<destination>{16305cb0-0a7e-4bee-8732-946923b6f8f5}</destination>
			<destination>{67f04e13-43f4-4216-bebf-595ba5444290}</destination>
		</relationship>
	</object>
	<object class="MixerBusPanner" id="{59499838-5217-469e-93ae-0335e5dce553}" />
	<object class="MixerBusFader" id="{dd3abd6c-e8f1-4128-8494-b23ba3a1752d}" />
	<object class="FadeCurve" id="{05eb4853-80df-4b6c-877e-851724d4035e}">
		<relationship name="startPoint">
			<destination>{4d03a679-94f1-46d5-8a7d-4c99a6c19302}</destination>
		</relationship>
		<relationship name="endPoint">
			<destination>{3d901239-12e8-4c19-85f5-06fa2c310bad}</destination>
		</relationship>
	</object>
	<object class="Automator" id="{073b6dc3-8401-4ed9-bdb1-5968bfe86d37}">
		<property name="nameOfPropertyBeingAutomated">
			<value>volume</value>
		</property>
	</object>
	<object class="MixerBusEffectChain" id="{38ef1cd4-1a05-4c6a-9699-2012ae094c9f}">
		<relationship name="effects">
			<destination>{1d7c84aa-c589-4b41-a985-bc20848360b4}</destination>
			<destination>{fd9dce7c-8a3e-4ba4-8227-c5d5ebac5fae}</destination>
		</relationship>
	</object>
	<object class="MixerBusPanner" id="{455c420a-4e02-4d39-a3fd-e0e42920ee1b}" />
	<object class="MixerBusEffectChain" id="{19208194-d291-49cf-b7a4-17d2797cdeb0}">
		<relationship name="effects">
			<destination>{be767077-904b-402b-abfb-c77c091315f9}</destination>
			<destination>{464ed2a1-e9e0-45a0-966f-9cebcf979287}</destination>
		</relationship>
	</object>
	<object class="MixerBusPanner" id="{d64d4f67-1305-4f48-93e7-524becf09849}" />
	<object class="MixerBusFader" id="{16305cb0-0a7e-4bee-8732-946923b6f8f5}" />
	<object class="GainEffect" id="{67f04e13-43f4-4216-bebf-595ba5444290}">
		<property name="gain">
			<value>-30</value>
		</property>
	</object>
	<object class="AutomationPoint" id="{4d03a679-94f1-46d5-8a7d-4c99a6c19302}">
		<property name="position">
			<value>15</value>
		</property>
		<property name="value">
			<value>1</value>
		</property>
		<property name="curveShape">
			<value>0.25471893</value>
		</property>
	</object>
	<object class="AutomationPoint" id="{3d901239-12e8-4c19-85f5-06fa2c310bad}">
		<property name="position">
			<value>24</value>
		</property>
		<property name="value">
			<value>0</value>
		</property>
	</object>
	<object class="MixerBusFader" id="{1d7c84aa-c589-4b41-a985-bc20848360b4}" />
	<object class="GainEffect" id="{fd9dce7c-8a3e-4ba4-8227-c5d5ebac5fae}" />
	<object class="MixerBusFader" id="{be767077-904b-402b-abfb-c77c091315f9}" />
	<object class="GainEffect" id="{464ed2a1-e9e0-45a0-966f-9cebcf979287}" />
</objects>
