<?xml version="1.0" encoding="UTF-8"?>
<objects serializationModel="Studio.02.02.00">
	<object class="Event" id="{a7996f29-40cb-485c-ad43-6f4ca30faf78}">
		<property name="name">
			<value>ko_chat_9</value>
		</property>
		<property name="outputFormat">
			<value>0</value>
		</property>
		<relationship name="folder">
			<destination>{4e8ed4db-b4ad-49fc-a7ae-e7a6d64d9b4f}</destination>
		</relationship>
		<relationship name="mixer">
			<destination>{bc5b6f3a-6774-4d85-a1bd-9d3df8fae068}</destination>
		</relationship>
		<relationship name="masterTrack">
			<destination>{766fddc9-5fae-4f8c-a469-bfa41326c525}</destination>
		</relationship>
		<relationship name="mixerInput">
			<destination>{accb65c6-1c6f-4468-ab71-eede6902da72}</destination>
		</relationship>
		<relationship name="automatableProperties">
			<destination>{46dc5f3b-609d-4191-919f-cd08c10fe0a3}</destination>
		</relationship>
		<relationship name="markerTracks">
			<destination>{f6d96983-1937-49bf-b0c5-1d5c6202c614}</destination>
		</relationship>
		<relationship name="groupTracks">
			<destination>{773d00e0-f18b-4f69-b19e-2bb6cd92ca81}</destination>
		</relationship>
		<relationship name="timeline">
			<destination>{1009b62e-5e67-4d11-8710-cf8ef91b16e1}</destination>
		</relationship>
		<relationship name="parameters">
			<destination>{da84963d-889a-439e-9d0d-54b81e5833ba}</destination>
		</relationship>
	</object>
	<object class="EventMixer" id="{bc5b6f3a-6774-4d85-a1bd-9d3df8fae068}">
		<relationship name="masterBus">
			<destination>{3dc6b39c-d8ad-424d-b844-4d7b89a3fa13}</destination>
		</relationship>
	</object>
	<object class="MasterTrack" id="{766fddc9-5fae-4f8c-a469-bfa41326c525}">
		<relationship name="mixerGroup">
			<destination>{3dc6b39c-d8ad-424d-b844-4d7b89a3fa13}</destination>
		</relationship>
	</object>
	<object class="MixerInput" id="{accb65c6-1c6f-4468-ab71-eede6902da72}">
		<relationship name="effectChain">
			<destination>{feec2a63-6719-4177-ab94-d6e38979717d}</destination>
		</relationship>
		<relationship name="panner">
			<destination>{b1b25825-7fea-4bef-9923-bfbca8d9ead1}</destination>
		</relationship>
		<relationship name="output">
			<destination>{4d2d2429-e5e0-47c0-9e15-a7434a93d1c4}</destination>
		</relationship>
	</object>
	<object class="EventAutomatableProperties" id="{46dc5f3b-609d-4191-919f-cd08c10fe0a3}">
		<property name="maxVoices">
			<value>1</value>
		</property>
		<property name="voiceStealing">
			<value>3</value>
		</property>
		<property name="priority">
			<value>4</value>
		</property>
	</object>
	<object class="MarkerTrack" id="{f6d96983-1937-49bf-b0c5-1d5c6202c614}" />
	<object class="GroupTrack" id="{773d00e0-f18b-4f69-b19e-2bb6cd92ca81}">
		<relationship name="modules">
			<destination>{da01a9bb-70c9-44d9-a341-8060b10d41f9}</destination>
		</relationship>
		<relationship name="mixerGroup">
			<destination>{aa2f8dc2-2f2a-44c5-95d9-a78ac59a187b}</destination>
		</relationship>
	</object>
	<object class="Timeline" id="{1009b62e-5e67-4d11-8710-cf8ef91b16e1}" />
	<object class="ParameterProxy" id="{da84963d-889a-439e-9d0d-54b81e5833ba}">
		<relationship name="modules">
			<destination>{da01a9bb-70c9-44d9-a341-8060b10d41f9}</destination>
		</relationship>
		<relationship name="preset">
			<destination>{435befca-bc53-458c-84cc-eab6efb2eee9}</destination>
		</relationship>
	</object>
	<object class="EventMixerMaster" id="{3dc6b39c-d8ad-424d-b844-4d7b89a3fa13}">
		<relationship name="effectChain">
			<destination>{a8ca5659-e5b2-49c1-a46a-2332e45fd830}</destination>
		</relationship>
		<relationship name="panner">
			<destination>{a8a50869-0cf6-46a2-b5b5-33e404f5abb4}</destination>
		</relationship>
		<relationship name="mixer">
			<destination>{bc5b6f3a-6774-4d85-a1bd-9d3df8fae068}</destination>
		</relationship>
	</object>
	<object class="MixerBusEffectChain" id="{feec2a63-6719-4177-ab94-d6e38979717d}">
		<relationship name="effects">
			<destination>{b80a1f67-9cf0-4b5e-ab80-94eba79194cb}</destination>
		</relationship>
	</object>
	<object class="MixerBusPanner" id="{b1b25825-7fea-4bef-9923-bfbca8d9ead1}" />
	<object class="MultiSound" id="{da01a9bb-70c9-44d9-a341-8060b10d41f9}">
		<property name="triggerProbabilityEnabled">
			<value>true</value>
		</property>
		<property name="voiceStealing">
			<value>3</value>
		</property>
		<property name="name">
			<value>/kor/common/kor_chat_9</value>
		</property>
		<property name="looping">
			<value>true</value>
		</property>
		<property name="playCount">
			<value>3</value>
		</property>
		<property name="playlistMode">
			<value>2</value>
		</property>
		<relationship name="sounds">
			<destination>{7bd2ef7e-c385-4fe8-a47f-61fbf4ebffc4}</destination>
			<destination>{3e65914e-2626-4e32-bf36-878ef30b0009}</destination>
			<destination>{6e97c417-080d-4296-b35a-5b585dffc074}</destination>
		</relationship>
	</object>
	<object class="EventMixerGroup" id="{aa2f8dc2-2f2a-44c5-95d9-a78ac59a187b}">
		<property name="volume">
			<value>-8</value>
		</property>
		<property name="name">
			<value>layer00</value>
		</property>
		<relationship name="effectChain">
			<destination>{44e0638f-3187-40c6-84a1-369d939b6e58}</destination>
		</relationship>
		<relationship name="panner">
			<destination>{4a758152-3722-4214-a885-f3de1d60410e}</destination>
		</relationship>
		<relationship name="output">
			<destination>{3dc6b39c-d8ad-424d-b844-4d7b89a3fa13}</destination>
		</relationship>
	</object>
	<object class="MixerBusEffectChain" id="{a8ca5659-e5b2-49c1-a46a-2332e45fd830}">
		<relationship name="effects">
			<destination>{1e8f19a8-c206-4c39-89a1-6aa838de28fa}</destination>
		</relationship>
	</object>
	<object class="MixerBusPanner" id="{a8a50869-0cf6-46a2-b5b5-33e404f5abb4}" />
	<object class="MixerBusFader" id="{b80a1f67-9cf0-4b5e-ab80-94eba79194cb}" />
	<object class="SingleSound" id="{7bd2ef7e-c385-4fe8-a47f-61fbf4ebffc4}">
		<property name="triggerProbabilityEnabled">
			<value>true</value>
		</property>
		<property name="voiceStealing">
			<value>3</value>
		</property>
		<relationship name="audioFile">
			<destination>{0ce68bcc-10f8-4e62-9567-659b25d889b0}</destination>
		</relationship>
	</object>
	<object class="SingleSound" id="{3e65914e-2626-4e32-bf36-878ef30b0009}">
		<property name="triggerProbabilityEnabled">
			<value>true</value>
		</property>
		<property name="voiceStealing">
			<value>3</value>
		</property>
		<relationship name="audioFile">
			<destination>{27e51573-4aa7-4f12-80c9-23f00453ca65}</destination>
		</relationship>
	</object>
	<object class="SingleSound" id="{6e97c417-080d-4296-b35a-5b585dffc074}">
		<property name="triggerProbabilityEnabled">
			<value>true</value>
		</property>
		<property name="voiceStealing">
			<value>3</value>
		</property>
		<relationship name="audioFile">
			<destination>{f4f7b2ea-9c38-45bf-9822-bdd60cf855e2}</destination>
		</relationship>
	</object>
	<object class="MixerBusEffectChain" id="{44e0638f-3187-40c6-84a1-369d939b6e58}">
		<relationship name="effects">
			<destination>{f8960124-171e-4306-853b-f1a9a69c1948}</destination>
			<destination>{820294cb-013c-4f69-a28f-3daa6cf42aca}</destination>
		</relationship>
	</object>
	<object class="MixerBusPanner" id="{4a758152-3722-4214-a885-f3de1d60410e}" />
	<object class="MixerBusFader" id="{1e8f19a8-c206-4c39-89a1-6aa838de28fa}" />
	<object class="MixerBusFader" id="{f8960124-171e-4306-853b-f1a9a69c1948}" />
	<object class="GainEffect" id="{820294cb-013c-4f69-a28f-3daa6cf42aca}" />
</objects>
