<?xml version="1.0" encoding="UTF-8"?>
<objects serializationModel="Studio.01.10.00">
    <object class="Event" id="{ea26b6b9-2bd4-44c3-a483-b7536cb6bf2b}">
        <property name="name">
            <value>voice_message_attacking_target_0</value>
        </property>
        <property name="outputFormat">
            <value>0</value>
        </property>
        <relationship name="folder">
            <destination>{e1b6bb12-d598-4bc0-b015-68561fe303ed}</destination>
        </relationship>
        <relationship name="mixer">
            <destination>{386033c4-9462-4896-ad73-a523b8815c7b}</destination>
        </relationship>
        <relationship name="masterTrack">
            <destination>{eb5031a1-ad49-4572-af0d-f8c696240fac}</destination>
        </relationship>
        <relationship name="mixerInput">
            <destination>{e79a52b3-6418-4694-9089-c46360ebe497}</destination>
        </relationship>
        <relationship name="automatableProperties">
            <destination>{db0600f2-8de2-457c-9fd5-a51e3bad1abb}</destination>
        </relationship>
        <relationship name="markerTracks">
            <destination>{4ad9e895-c93f-432d-8114-2ef2704baaf8}</destination>
        </relationship>
        <relationship name="groupTracks">
            <destination>{dbb23d52-65d2-4fe6-aff0-93759da1e73c}</destination>
        </relationship>
        <relationship name="timeline">
            <destination>{eb775c66-5f21-489b-9259-f7f7b2979b10}</destination>
        </relationship>
        <relationship name="parameters">
            <destination>{270dde97-4f21-458a-aebf-b6c9427802df}</destination>
        </relationship>
        <relationship name="banks">
            <destination>{79f9e0ea-9562-4d94-acc1-732e43a7fd96}</destination>
        </relationship>
    </object>
    <object class="EventMixer" id="{386033c4-9462-4896-ad73-a523b8815c7b}">
        <relationship name="masterBus">
            <destination>{e8639c71-b782-40e3-b728-3c4cd4615041}</destination>
        </relationship>
    </object>
    <object class="MasterTrack" id="{eb5031a1-ad49-4572-af0d-f8c696240fac}">
        <relationship name="mixerGroup">
            <destination>{e8639c71-b782-40e3-b728-3c4cd4615041}</destination>
        </relationship>
    </object>
    <object class="MixerInput" id="{e79a52b3-6418-4694-9089-c46360ebe497}">
        <relationship name="effectChain">
            <destination>{be4fc8c5-6e0f-4c17-ad66-1ab469f38fff}</destination>
        </relationship>
        <relationship name="panner">
            <destination>{e227efde-0880-482a-b082-1957e718615f}</destination>
        </relationship>
        <relationship name="output">
            <destination>{51dca951-e1c2-4de2-8b33-cd9c60eaaf2a}</destination>
        </relationship>
    </object>
    <object class="EventAutomatableProperties" id="{db0600f2-8de2-457c-9fd5-a51e3bad1abb}">
        <property name="maxVoices">
            <value>1</value>
        </property>
        <property name="voiceStealing">
            <value>3</value>
        </property>
        <property name="priority">
            <value>4</value>
        </property>
    </object>
    <object class="MarkerTrack" id="{4ad9e895-c93f-432d-8114-2ef2704baaf8}"/>
    <object class="GroupTrack" id="{dbb23d52-65d2-4fe6-aff0-93759da1e73c}">
        <relationship name="modules">
            <destination>{d8e016ab-ae36-46a4-9303-368656fecd63}</destination>
        </relationship>
        <relationship name="mixerGroup">
            <destination>{51a3ca04-1c9b-47f9-8953-52b49b3c8ab1}</destination>
        </relationship>
    </object>
    <object class="Timeline" id="{eb775c66-5f21-489b-9259-f7f7b2979b10}"/>
    <object class="ParameterProxy" id="{270dde97-4f21-458a-aebf-b6c9427802df}">
        <relationship name="modules">
            <destination>{d8e016ab-ae36-46a4-9303-368656fecd63}</destination>
        </relationship>
        <relationship name="preset">
            <destination>{435befca-bc53-458c-84cc-eab6efb2eee9}</destination>
        </relationship>
    </object>
    <object class="EventMixerMaster" id="{e8639c71-b782-40e3-b728-3c4cd4615041}">
        <relationship name="effectChain">
            <destination>{0e815c12-14a1-4bce-ac78-91e86d7ca00b}</destination>
        </relationship>
        <relationship name="panner">
            <destination>{eba7043f-5c1d-4797-a12f-3d61ea4c2cd2}</destination>
        </relationship>
        <relationship name="mixer">
            <destination>{386033c4-9462-4896-ad73-a523b8815c7b}</destination>
        </relationship>
    </object>
    <object class="MixerBusEffectChain" id="{be4fc8c5-6e0f-4c17-ad66-1ab469f38fff}">
        <relationship name="effects">
            <destination>{af03cf79-7b74-49de-9f54-06a5092647b0}</destination>
        </relationship>
    </object>
    <object class="MixerBusPanner" id="{e227efde-0880-482a-b082-1957e718615f}"/>
    <object class="MultiSound" id="{d8e016ab-ae36-46a4-9303-368656fecd63}">
        <property name="triggerProbabilityEnabled">
            <value>true</value>
        </property>
        <property name="voiceStealing">
            <value>3</value>
        </property>
        <property name="name">
            <value>/dialogs_wopl/english/voise_messages/voice4/voice_message_attacking_target_0_1</value>
        </property>
        <property name="playlistMode">
            <value>0</value>
        </property>
        <relationship name="sounds">
            <destination>{4500df64-fce7-4969-a10e-3097e0c10066}</destination>
            <destination>{7b8f0e85-853d-4418-8153-47006976f504}</destination>
            <destination>{f2eed078-70a0-4deb-b3d3-1db9d474dd2d}</destination>
        </relationship>
    </object>
    <object class="EventMixerGroup" id="{51a3ca04-1c9b-47f9-8953-52b49b3c8ab1}">
        <property name="name">
            <value>layer00</value>
        </property>
        <relationship name="effectChain">
            <destination>{ce9716a1-1092-4037-af0d-caeca41f5e07}</destination>
        </relationship>
        <relationship name="panner">
            <destination>{26048929-1d98-4a29-894b-54e3dff3d4b5}</destination>
        </relationship>
        <relationship name="output">
            <destination>{e8639c71-b782-40e3-b728-3c4cd4615041}</destination>
        </relationship>
    </object>
    <object class="MixerBusEffectChain" id="{0e815c12-14a1-4bce-ac78-91e86d7ca00b}">
        <relationship name="effects">
            <destination>{3a64f433-22b0-4bbb-825a-6223d5d79de0}</destination>
        </relationship>
    </object>
    <object class="MixerBusPanner" id="{eba7043f-5c1d-4797-a12f-3d61ea4c2cd2}"/>
    <object class="MixerBusFader" id="{af03cf79-7b74-49de-9f54-06a5092647b0}"/>
    <object class="ProgrammerSound" id="{4500df64-fce7-4969-a10e-3097e0c10066}">
        <property name="name">
            <value>voice_messages/voice3/voice_message_attacking_target_0_1</value>
        </property>
    </object>
    <object class="ProgrammerSound" id="{7b8f0e85-853d-4418-8153-47006976f504}">
        <property name="name">
            <value>voice_messages/voice3/voice_message_attacking_target_0_2</value>
        </property>
    </object>
    <object class="ProgrammerSound" id="{f2eed078-70a0-4deb-b3d3-1db9d474dd2d}">
        <property name="name">
            <value>voice_messages/voice3/voice_message_attacking_target_0_3</value>
        </property>
    </object>
    <object class="MixerBusEffectChain" id="{ce9716a1-1092-4037-af0d-caeca41f5e07}">
        <relationship name="effects">
            <destination>{42f70005-db60-4db5-850a-f92333a0acdf}</destination>
            <destination>{8d66d324-5fb4-4b86-a4e2-98afda8f3769}</destination>
        </relationship>
    </object>
    <object class="MixerBusPanner" id="{26048929-1d98-4a29-894b-54e3dff3d4b5}"/>
    <object class="MixerBusFader" id="{3a64f433-22b0-4bbb-825a-6223d5d79de0}"/>
    <object class="MixerBusFader" id="{42f70005-db60-4db5-850a-f92333a0acdf}"/>
    <object class="GainEffect" id="{8d66d324-5fb4-4b86-a4e2-98afda8f3769}"/>
</objects>
