<?xml version="1.0" encoding="UTF-8"?>
<objects serializationModel="Studio.02.01.00">
	<object class="ParameterPreset" id="{9d5c06b4-d7a6-0ba4-3838-8673c6083d81}">
		<property name="name">
			<value>Distance</value>
		</property>
		<relationship name="folder">
			<destination>{464192bd-d51c-4539-9a23-ccd503f97dae}</destination>
		</relationship>
		<relationship name="parameter">
			<destination>{dd58c014-5f2c-48a3-8f9b-45c93483fe20}</destination>
		</relationship>
	</object>
	<object class="GameParameter" id="{dd58c014-5f2c-48a3-8f9b-45c93483fe20}">
		<property name="parameterType">
			<value>3</value>
		</property>
		<property name="maximum">
			<value>700</value>
		</property>
		<property name="initialValue">
			<value>0</value>
		</property>
		<property name="isExposedRecursively">
			<value>false</value>
		</property>
	</object>
</objects>
