<?xml version="1.0" encoding="UTF-8"?>
<objects serializationModel="Studio.01.10.00">
    <object class="AudioFile" id="{46fc3540-6c4e-46c0-8447-6156a766686d}">
        <property name="assetPath">
            <value>dialogs_wopl/russian/voice_messages/voice2/voice_message_sorry_2_3.wav</value>
        </property>
        <property name="frequencyInKHz">
            <value>22.0499992</value>
        </property>
        <property name="channelCount">
            <value>1</value>
        </property>
        <property name="length">
            <value>1.2298412698412697</value>
        </property>
        <relationship name="masterAssetFolder">
            <destination>{81dc2e2f-1fe8-4962-9976-ac27d7c0b961}</destination>
        </relationship>
    </object>
</objects>
