<?xml version="1.0" encoding="UTF-8"?>
<objects serializationModel="Studio.02.01.00">
	<object class="AudioFile" id="{6a20ade2-2c02-419b-9e74-94b185d4d72c}">
		<property name="assetPath">
			<value>tanks/weapon/cannons/cannons_close_modules/close_17_12_2021/cannon_01_shot-002.wav</value>
		</property>
		<property name="frequencyInKHz">
			<value>48</value>
		</property>
		<property name="channelCount">
			<value>2</value>
		</property>
		<property name="length">
			<value>2.3999999999999999</value>
		</property>
		<relationship name="masterAssetFolder">
			<destination>{81dc2e2f-1fe8-4962-9976-ac27d7c0b961}</destination>
		</relationship>
	</object>
</objects>
