<?xml version="1.0" encoding="UTF-8"?>
<objects serializationModel="Studio.01.10.00">
    <object class="AudioFile" id="{a38c2db1-1fcc-48a3-a0c1-298b81c4ee8d}">
        <property name="assetPath">
            <value>radio_chat/srb/voice2/srb_damaged_engine_v2_r5_t1_mood_low.wav</value>
        </property>
        <property name="frequencyInKHz">
            <value>22.0499992</value>
        </property>
        <property name="channelCount">
            <value>1</value>
        </property>
        <property name="length">
            <value>2.3800453514739228</value>
        </property>
        <relationship name="masterAssetFolder">
            <destination>{81dc2e2f-1fe8-4962-9976-ac27d7c0b961}</destination>
        </relationship>
    </object>
</objects>
