<?xml version="1.0" encoding="UTF-8"?>
<objects serializationModel="Studio.02.01.00">
	<object class="EncodingSetting" id="{07ad3a11-9f62-448d-b809-a92ad1330a19}">
		<property name="encodingFormat">
			<value>1</value>
		</property>
		<property name="quality">
			<value>37</value>
		</property>
		<property name="sampleRate">
			<value>44100</value>
		</property>
		<relationship name="platform">
			<destination>{79817437-9e34-4b5a-8618-959c7e404103}</destination>
		</relationship>
		<relationship name="encodable">
			<destination>{af4b6848-dca4-4b89-a80c-cbbd72ec92ac}</destination>
		</relationship>
	</object>
</objects>
