<?xml version="1.0" encoding="UTF-8"?>
<objects serializationModel="Studio.02.00.00">
	<object class="EncodingSetting" id="{17f1ee1e-3340-459b-9549-73bf757a442d}">
		<property name="encodingFormat">
			<value>1</value>
		</property>
		<property name="quality">
			<value>37</value>
		</property>
		<relationship name="platform">
			<destination>{79817437-9e34-4b5a-8618-959c7e404103}</destination>
		</relationship>
		<relationship name="encodable">
			<destination>{78cf5ad0-54a3-4ab4-bf2e-3c5b6b3e6eff}</destination>
		</relationship>
	</object>
</objects>
