<?xml version="1.0" encoding="UTF-8"?>
<objects serializationModel="Studio.02.01.00">
	<object class="EncodingSetting" id="{be02c76e-63ba-4704-8a8b-29db52feee44}">
		<property name="encodingFormat">
			<value>1</value>
		</property>
		<property name="quality">
			<value>37</value>
		</property>
		<property name="sampleRate">
			<value>44100</value>
		</property>
		<relationship name="platform">
			<destination>{79817437-9e34-4b5a-8618-959c7e404103}</destination>
		</relationship>
		<relationship name="encodable">
			<destination>{1e38a8da-c160-4b46-b5fb-850e2210b798}</destination>
		</relationship>
	</object>
</objects>
