<?xml version="1.0" encoding="UTF-8"?>
<objects serializationModel="Studio.02.00.00">
	<object class="EncodingSetting" id="{ef5c8e92-50de-4974-b150-55c6ac0f3777}">
		<property name="encodingFormat">
			<value>1</value>
		</property>
		<property name="quality">
			<value>37</value>
		</property>
		<property name="sampleRate">
			<value>22000</value>
		</property>
		<relationship name="platform">
			<destination>{79817437-9e34-4b5a-8618-959c7e404103}</destination>
		</relationship>
		<relationship name="encodable">
			<destination>{91378ad8-d356-4eb7-9662-48a670b9013d}</destination>
		</relationship>
	</object>
</objects>
